jira_review_reminder.py
jira_reviews_reminder-0.1.6.dist-info/LICENSE
jira_reviews_reminder-0.1.6.dist-info/METADATA
jira_reviews_reminder-0.1.6.dist-info/WHEEL
jira_reviews_reminder-0.1.6.dist-info/entry_points.txt
jira_reviews_reminder-0.1.6.dist-info/top_level.txt
jira_reviews_reminder-0.1.6.dist-info/RECORD
