Metadata-Version: 2.1
Name: jira-reviews-reminder
Version: 0.1.6
Summary: Notifies in Slack channel with a list of jira tickets that have pending review from x days. Adds the reviewer and PR details if exists.
Home-page: https://github.com/bkatwal/jira-review-reminder
Author: Bikas Katwal
Author-email: bikas.katwal10@gmail.com
License: MIT
Platform: UNKNOWN
Requires-Python: >=3
Requires-Dist: requests (==2.25.1)
Requires-Dist: slackclient (==2.9.3)
Requires-Dist: atlassian-python-api (==3.6.0)
Requires-Dist: python-dotenv (==0.15.0)
